squad_builder/__init__.py
squad_builder/api/__init__.py
squad_builder/api/cli.py
squad_builder/api/decorators.py
squad_builder/data_client/__init__.py
squad_builder/data_client/client.py
squad_builder/tasks/__init__.py
squad_builder/tasks/local_registry.py
tests/__init__.py
tests/test_data_client.py
squad_builder-0.1.9.dist-info/LICENSE
squad_builder-0.1.9.dist-info/METADATA
squad_builder-0.1.9.dist-info/WHEEL
squad_builder-0.1.9.dist-info/top_level.txt
squad_builder-0.1.9.dist-info/RECORD
