Metadata-Version: 2.1
Name: squad-builder
Version: 0.1.9
Summary: Unified cloud storage client for S3, Azure Blob, and GCP Storage
Home-page: https://github.com/yourusername/squad-builder
Author: Squad Builder Team
Author-email: info@example.com
Keywords: storage,s3,azure,gcp,cloud
Classifier: Development Status :: 3 - Alpha
Classifier: Intended Audience :: Developers
Classifier: License :: OSI Approved :: MIT License
Classifier: Programming Language :: Python :: 3
Classifier: Programming Language :: Python :: 3.7
Classifier: Programming Language :: Python :: 3.8
Classifier: Programming Language :: Python :: 3.9
Classifier: Programming Language :: Python :: 3.10
Requires-Python: >=3.7
License-File: LICENSE
Requires-Dist: requests>=2.25.0
Requires-Dist: boto3>=1.18.0
Requires-Dist: azure-storage-blob>=12.8.0
Requires-Dist: google-cloud-storage>=1.42.0
Requires-Dist: fastapi>=0.100.0
Requires-Dist: uvicorn>=0.22.0
Requires-Dist: pyyaml>=6.0
